rtl/lfsr_core.v
// ============================================================
// Module  : lfsr_core
// Project : AXI-Lite PRNG RTL2GDS
// Description:
//   4-bit Galois LFSR (Linear Feedback Shift Register)
//   Tap positions : [4, 0]  → polynomial x^4 + x^3 + 1
//   Maximum-length sequence: 2^4 - 1 = 15 unique states
//
//   Operation:
//     - Active-low synchronous reset; loads 'seed' value
//     - When enable=1, shifts every rising clock edge
//     - Output 'rand_out' holds current 4-bit random value
//
//   Feedback:
//     new_bit = rand_out[3] XOR rand_out[2]
//     shift  : {rand_out[2:0], new_bit}
// ============================================================

module lfsr_core (
    input  wire       clk,       // System clock
    input  wire       rst_n,     // Active-low synchronous reset
    input  wire       enable,    // Enable shifting (1 = run)
    input  wire [3:0] seed,      // Seed value loaded on reset
    output reg  [3:0] rand_out   // Current pseudo-random value
);

    // --------------------------------------------------------
    // Internal signal
    // --------------------------------------------------------
    wire feedback;

    // Galois LFSR feedback: XOR of tap positions 4 and 1
    // (bit indices 3 and 0 in 0-based)
    assign feedback = rand_out[3] ^ rand_out[0];

    // --------------------------------------------------------
    // Sequential logic : shift register
    // --------------------------------------------------------
    always @(posedge clk) begin
        if (!rst_n) begin
            // Load seed on reset; never allow all-zero state
            rand_out <= (seed == 4'b0000) ? 4'b0001 : seed;
        end
        else if (enable) begin
            // Shift left and insert feedback at LSB
            rand_out <= {rand_out[2:0], feedback};
        end
        // else: hold current value
    end

endmodule

tb/tb_lfsr_core.v
// ============================================================
// Testbench : tb_lfsr_core
// Purpose   : Unit test for the 4-bit LFSR core
//
// Tests performed:
//   1. Reset behaviour  – verify seed is loaded correctly
//   2. Zero-seed guard  – all-zero seed must default to 0001
//   3. Full sequence    – verify all 15 unique states appear
//   4. Enable control   – output must hold when enable=0
//   5. Re-seed          – changing seed mid-run restarts sequence
//
// How to run:
//   iverilog -o sim_lfsr tb/tb_lfsr_core.v rtl/lfsr_core.v
//   vvp sim_lfsr
//   gtkwave dump_lfsr.vcd   (optional waveform)
// ============================================================

`timescale 1ns/1ps

module tb_lfsr_core;

    // ── DUT signals ─────────────────────────────────────────
    reg        clk;
    reg        rst_n;
    reg        enable;
    reg  [3:0] seed;
    wire [3:0] rand_out;

    // ── Instantiate DUT ─────────────────────────────────────
    lfsr_core dut (
        .clk      (clk),
        .rst_n    (rst_n),
        .enable   (enable),
        .seed     (seed),
        .rand_out (rand_out)
    );

    // ── Clock generation : 10 ns period (100 MHz) ───────────
    initial clk = 0;
    always #5 clk = ~clk;

    // ── VCD dump ────────────────────────────────────────────
    initial begin
        $dumpfile("sim/dump_lfsr.vcd");
        $dumpvars(0, tb_lfsr_core);
    end

    // ── Helper task : apply reset ───────────────────────────
    task apply_reset;
        input [3:0] s;
        begin
            seed  = s;
            rst_n = 0;
            @(posedge clk); #1;
            @(posedge clk); #1;
            rst_n = 1;
        end
    endtask

    // ── Helper task : AXI-like wait cycles ──────────────────
    task wait_cycles;
        input integer n;
        integer i;
        begin
            for (i = 0; i < n; i = i + 1)
                @(posedge clk);
            #1;
        end
    endtask

    // ── Test tracking ───────────────────────────────────────
    integer pass_cnt;
    integer fail_cnt;

    task check;
        input [63:0] test_id;
        input        condition;
        input [127:0] msg;
        begin
            if (condition) begin
                $display("  [PASS] Test %0d : %s", test_id, msg);
                pass_cnt = pass_cnt + 1;
            end else begin
                $display("  [FAIL] Test %0d : %s  (rand_out=%b)", test_id, msg, rand_out);
                fail_cnt = fail_cnt + 1;
            end
        end
    endtask

    // ── Main test sequence ───────────────────────────────────
    integer i;
    reg [3:0] prev_val;
    reg [14:0] seen_mask;   // Bit i set if value (i+1) was seen
    integer unique_count;

    initial begin
        // Init
        pass_cnt = 0;
        fail_cnt = 0;
        enable   = 0;
        seed     = 4'b0001;
        rst_n    = 1;
        #3;

        $display("\n========================================");
        $display("   LFSR Core Unit Tests");
        $display("========================================");

        // ------------------------------------------------
        // TEST 1: Reset with seed=1
        // ------------------------------------------------
        $display("\n--- Test 1: Reset loads seed correctly ---");
        apply_reset(4'b0001);
        check(1, rand_out === 4'b0001, "rand_out == seed after reset");

        // ------------------------------------------------
        // TEST 2: Zero-seed guard (must load 0001 not 0000)
        // ------------------------------------------------
        $display("\n--- Test 2: Zero-seed guard ---");
        apply_reset(4'b0000);
        check(2, rand_out !== 4'b0000, "All-zero seed replaced with 0001");
        check(3, rand_out === 4'b0001, "Guarded seed value is 4'b0001");

        // ------------------------------------------------
        // TEST 3: Enable=0 holds output
        // ------------------------------------------------
        $display("\n--- Test 3: Enable=0 freezes output ---");
        apply_reset(4'b0101);
        enable   = 0;
        prev_val = rand_out;
        wait_cycles(5);
        check(4, rand_out === prev_val, "Output unchanged when enable=0");

        // ------------------------------------------------
        // TEST 4: Full 15-state sequence with seed=0001
        // ------------------------------------------------
        $display("\n--- Test 4: 15 unique states in full sequence ---");
        apply_reset(4'b0001);
        enable      = 1;
        seen_mask   = 15'b0;
        unique_count= 0;

        // The starting seed counts as first state
        if (rand_out != 4'b0000) begin
            seen_mask[rand_out - 1] = 1'b1;
            unique_count = unique_count + 1;
        end

        for (i = 0; i < 15; i = i + 1) begin
            @(posedge clk); #1;
            if (rand_out != 4'b0000 && !seen_mask[rand_out - 1]) begin
                seen_mask[rand_out - 1] = 1'b1;
                unique_count = unique_count + 1;
            end
        end

        check(5, unique_count === 15, "All 15 unique non-zero states observed");
        $display("         Seen mask : %015b", seen_mask);
        $display("         Unique values : %0d / 15", unique_count);

        // ------------------------------------------------
        // TEST 5: Sequence repeats after 15 steps
        // ------------------------------------------------
        $display("\n--- Test 5: Sequence repeats exactly at 15 steps ---");
        apply_reset(4'b0001);
        enable   = 1;
        prev_val = rand_out;     // = seed = 4'b0001

        // Advance 15 cycles – should return to same value
        wait_cycles(15);
        check(6, rand_out === prev_val, "State after 15 cycles == initial seed");

        // ------------------------------------------------
        // TEST 6: Different seeds produce valid sequences
        // ------------------------------------------------
        $display("\n--- Test 6: Seed=1010 generates unique sequence ---");
        apply_reset(4'b1010);
        enable      = 1;
        seen_mask   = 15'b0;
        unique_count= 0;

        if (rand_out != 4'b0000) begin
            seen_mask[rand_out - 1] = 1'b1;
            unique_count = unique_count + 1;
        end

        for (i = 0; i < 15; i = i + 1) begin
            @(posedge clk); #1;
            if (rand_out != 4'b0000 && !seen_mask[rand_out - 1]) begin
                seen_mask[rand_out - 1] = 1'b1;
                unique_count = unique_count + 1;
            end
        end

        check(7, unique_count === 15, "15 unique states from seed 1010");

        // ------------------------------------------------
        // Print the actual sequence for reference
        // ------------------------------------------------
        $display("\n--- Printing LFSR sequence from seed=0001 ---");
        apply_reset(4'b0001);
        enable = 1;
        $display("  Cycle  0 : %04b (%0d)", rand_out, rand_out);
        for (i = 1; i <= 15; i = i + 1) begin
            @(posedge clk); #1;
            $display("  Cycle %2d : %04b (%0d)", i, rand_out, rand_out);
        end

        // ------------------------------------------------
        // Summary
        // ------------------------------------------------
        $display("\n========================================");
        $display("  Results : %0d PASS  |  %0d FAIL", pass_cnt, fail_cnt);
        $display("========================================\n");

        if (fail_cnt == 0)
            $display("  ALL TESTS PASSED ✓\n");
        else
            $display("  SOME TESTS FAILED ✗ – check output above\n");

        $finish;
    end

    // ── Timeout watchdog ─────────────────────────────────────
    initial begin
        #10000;
        $display("[ERROR] Simulation timeout!");
        $finish;
    end

endmodule

sim/dump_lfsr.vcd
$date
	Wed May 27 22:57:25 2026
$end
$version
	Icarus Verilog
$end
$timescale
	1ps
$end
$scope module tb_lfsr_core $end
$var wire 4 ! rand_out [3:0] $end
$var reg 1 " clk $end
$var reg 1 # enable $end
$var reg 4 $ prev_val [3:0] $end
$var reg 1 % rst_n $end
$var reg 4 & seed [3:0] $end
$var reg 15 ' seen_mask [14:0] $end
$var integer 32 ( fail_cnt [31:0] $end
$var integer 32 ) i [31:0] $end
$var integer 32 * pass_cnt [31:0] $end
$var integer 32 + unique_count [31:0] $end
$scope module dut $end
$var wire 1 " clk $end
$var wire 1 # enable $end
$var wire 1 , feedback $end
$var wire 1 % rst_n $end
$var wire 4 - seed [3:0] $end
$var reg 4 . rand_out [3:0] $end
$upscope $end
$scope task apply_reset $end
$var reg 4 / s [3:0] $end
$upscope $end
$scope task check $end
$var reg 1 0 condition $end
$var reg 128 1 msg [127:0] $end
$var reg 64 2 test_id [63:0] $end
$upscope $end
$scope task wait_cycles $end
$var integer 32 3 i [31:0] $end
$var integer 32 4 n [31:0] $end
$upscope $end
$upscope $end
$enddefinitions $end
$comment Show the parameter values. $end
$dumpall
$end
#0
$dumpvars
bx 4
bx 3
bx 2
bx 1
x0
bx /
bx .
b1 -
x,
bx +
b0 *
bx )
b0 (
bx '
b1 &
1%
bx $
0#
0"
bx !
$end
#3000
0%
b1 /
#5000
1,
b1 !
b1 .
1"
#10000
0"
#15000
1"
#16000
b0 &
b0 -
b0 /
b1 *
b1110011011001010110010101100100001000000110000101100110011101000110010101110010001000000111001001100101011100110110010101110100 1
10
b1 2
0%
#20000
0"
#25000
1"
#30000
0"
#35000
1"
#36000
b101 &
b101 -
b101 /
b11 *
b1110110011000010110110001110101011001010010000001101001011100110010000000110100001001110110001000110000001100000011000000110001 1
b11 2
0%
#40000
0"
#45000
b101 !
b101 .
1"
#50000
0"
#55000
1"
#56000
b0 3
b101 4
b101 $
1%
#60000
0"
#65000
b1 3
1"
#70000
0"
#75000
b10 3
1"
#80000
0"
#85000
b11 3
1"
#90000
0"
#95000
b100 3
1"
#100000
0"
#105000
b101 3
1"
#106000
0%
b1 &
b1 -
b1 /
b100 *
b1100101011001000010000001110111011010000110010101101110001000000110010101101110011000010110001001101100011001010011110100110000 1
b100 2
#110000
0"
#115000
b1 !
b1 .
1"
#120000
0"
#125000
1"
#126000
b0 )
b1 +
b1 '
1#
1%
#130000
0"
#135000
b11 !
b11 .
1"
#136000
b1 )
b10 +
b101 '
#140000
0"
#145000
b111 !
b111 .
1"
#146000
b10 )
b11 +
b1000101 '
#150000
0"
#155000
0,
b1111 !
b1111 .
1"
#156000
b11 )
b100 +
b100000001000101 '
#160000
0"
#165000
1,
b1110 !
b1110 .
1"
#166000
b100 )
b101 +
b110000001000101 '
#170000
0"
#175000
0,
b1101 !
b1101 .
1"
#176000
b101 )
b110 +
b111000001000101 '
#180000
0"
#185000
1,
b1010 !
b1010 .
1"
#186000
b110 )
b111 +
b111001001000101 '
#190000
0"
#195000
b101 !
b101 .
1"
#196000
b111 )
b1000 +
b111001001010101 '
#200000
0"
#205000
0,
b1011 !
b1011 .
1"
#206000
b1000 )
b1001 +
b111011001010101 '
#210000
0"
#215000
b110 !
b110 .
1"
#216000
b1001 )
b1010 +
b111011001110101 '
#220000
0"
#225000
1,
b1100 !
b1100 .
1"
#226000
b1010 )
b1011 +
b111111001110101 '
#230000
0"
#235000
0,
b1001 !
b1001 .
1"
#236000
b1011 )
b1100 +
b111111101110101 '
#240000
0"
#245000
b10 !
b10 .
1"
#246000
b1100 )
b1101 +
b111111101110111 '
#250000
0"
#255000
b100 !
b100 .
1"
#256000
b1101 )
b1110 +
b111111101111111 '
#260000
0"
#265000
1,
b1000 !
b1000 .
1"
#266000
b1110 )
b1111 +
b111111111111111 '
#270000
0"
#275000
b1 !
b1 .
1"
#276000
0%
b101 *
b100000011100110111010001100001011101000110010101110011001000000110111101100010011100110110010101110010011101100110010101100100 1
b101 2
b1111 )
#280000
0"
#285000
1"
#290000
0"
#295000
1"
#296000
b0 3
b1111 4
b1 $
1%
#300000
0"
#305000
b11 !
b11 .
b1 3
1"
#310000
0"
#315000
b111 !
b111 .
b10 3
1"
#320000
0"
#325000
0,
b1111 !
b1111 .
b11 3
1"
#330000
0"
#335000
1,
b1110 !
b1110 .
b100 3
1"
#340000
0"
#345000
0,
b1101 !
b1101 .
b101 3
1"
#350000
0"
#355000
1,
b1010 !
b1010 .
b110 3
1"
#360000
0"
#365000
b101 !
b101 .
b111 3
1"
#370000
0"
#375000
0,
b1011 !
b1011 .
b1000 3
1"
#380000
0"
#385000
b110 !
b110 .
b1001 3
1"
#390000
0"
#395000
1,
b1100 !
b1100 .
b1010 3
1"
#400000
0"
#405000
0,
b1001 !
b1001 .
b1011 3
1"
#410000
0"
#415000
b10 !
b10 .
b1100 3
1"
#420000
0"
#425000
b100 !
b100 .
b1101 3
1"
#430000
0"
#435000
1,
b1000 !
b1000 .
b1110 3
1"
#440000
0"
#445000
b1 !
b1 .
b1111 3
1"
#446000
0%
b1010 &
b1010 -
b1010 /
b110 *
b100000001111010011110100100000011010010110111001101001011101000110100101100001011011000010000001110011011001010110010101100100 1
b110 2
#450000
0"
#455000
b1010 !
b1010 .
1"
#460000
0"
#465000
1"
#466000
b0 )
b1 +
b1000000000 '
1%
#470000
0"
#475000
b101 !
b101 .
1"
#476000
b1 )
b10 +
b1000010000 '
#480000
0"
#485000
0,
b1011 !
b1011 .
1"
#486000
b10 )
b11 +
b11000010000 '
#490000
0"
#495000
b110 !
b110 .
1"
#496000
b11 )
b100 +
b11000110000 '
#500000
0"
#505000
1,
b1100 !
b1100 .
1"
#506000
b100 )
b101 +
b111000110000 '
#510000
0"
#515000
0,
b1001 !
b1001 .
1"
#516000
b101 )
b110 +
b111100110000 '
#520000
0"
#525000
b10 !
b10 .
1"
#526000
b110 )
b111 +
b111100110010 '
#530000
0"
#535000
b100 !
b100 .
1"
#536000
b111 )
b1000 +
b111100111010 '
#540000
0"
#545000
1,
b1000 !
b1000 .
1"
#546000
b1000 )
b1001 +
b111110111010 '
#550000
0"
#555000
b1 !
b1 .
1"
#556000
b1001 )
b1010 +
b111110111011 '
#560000
0"
#565000
b11 !
b11 .
1"
#566000
b1010 )
b1011 +
b111110111111 '
#570000
0"
#575000
b111 !
b111 .
1"
#576000
b1011 )
b1100 +
b111111111111 '
#580000
0"
#585000
0,
b1111 !
b1111 .
1"
#586000
b1100 )
b1101 +
b100111111111111 '
#590000
0"
#595000
1,
b1110 !
b1110 .
1"
#596000
b1101 )
b1110 +
b110111111111111 '
#600000
0"
#605000
0,
b1101 !
b1101 .
1"
#606000
b1110 )
b1111 +
b111111111111111 '
#610000
0"
#615000
1,
b1010 !
b1010 .
1"
#616000
0%
b1 &
b1 -
b1 /
b111 *
b1110011001000000110011001110010011011110110110100100000011100110110010101100101011001000010000000110001001100000011000100110000 1
b111 2
b1111 )
#620000
0"
#625000
b1 !
b1 .
1"
#630000
0"
#635000
1"
#636000
b1 )
1%
#640000
0"
#645000
b11 !
b11 .
1"
#646000
b10 )
#650000
0"
#655000
b111 !
b111 .
1"
#656000
b11 )
#660000
0"
#665000
0,
b1111 !
b1111 .
1"
#666000
b100 )
#670000
0"
#675000
1,
b1110 !
b1110 .
1"
#676000
b101 )
#680000
0"
#685000
0,
b1101 !
b1101 .
1"
#686000
b110 )
#690000
0"
#695000
1,
b1010 !
b1010 .
1"
#696000
b111 )
#700000
0"
#705000
b101 !
b101 .
1"
#706000
b1000 )
#710000
0"
#715000
0,
b1011 !
b1011 .
1"
#716000
b1001 )
#720000
0"
#725000
b110 !
b110 .
1"
#726000
b1010 )
#730000
0"
#735000
1,
b1100 !
b1100 .
1"
#736000
b1011 )
#740000
0"
#745000
0,
b1001 !
b1001 .
1"
#746000
b1100 )
#750000
0"
#755000
b10 !
b10 .
1"
#756000
b1101 )
#760000
0"
#765000
b100 !
b100 .
1"
#766000
b1110 )
#770000
0"
#775000
1,
b1000 !
b1000 .
1"
#776000
b1111 )
#780000
0"
#785000
b1 !
b1 .
1"
#786000
b10000 )
