rtl/lfsr_core.v
// ============================================================
// Module  : lfsr_core
// Project : AXI-Lite PRNG RTL2GDS
// Description:
//   4-bit Galois LFSR (Linear Feedback Shift Register)
//   Tap positions : [4, 0]  → polynomial x^4 + x^3 + 1
//   Maximum-length sequence: 2^4 - 1 = 15 unique states
//
//   Operation:
//     - Active-low synchronous reset; loads 'seed' value
//     - When enable=1, shifts every rising clock edge
//     - Output 'rand_out' holds current 4-bit random value
//
//   Feedback:
//     new_bit = rand_out[3] XOR rand_out[2]
//     shift  : {rand_out[2:0], new_bit}
// ============================================================

module lfsr_core (
    input  wire       clk,       // System clock
    input  wire       rst_n,     // Active-low synchronous reset
    input  wire       enable,    // Enable shifting (1 = run)
    input  wire [3:0] seed,      // Seed value loaded on reset
    output reg  [3:0] rand_out   // Current pseudo-random value
);

    // --------------------------------------------------------
    // Internal signal
    // --------------------------------------------------------
    wire feedback;

    // Galois LFSR feedback: XOR of tap positions 4 and 1
    // (bit indices 3 and 0 in 0-based)
    assign feedback = rand_out[3] ^ rand_out[0];

    // --------------------------------------------------------
    // Sequential logic : shift register
    // --------------------------------------------------------
    always @(posedge clk) begin
        if (!rst_n) begin
            // Load seed on reset; never allow all-zero state
            rand_out <= (seed == 4'b0000) ? 4'b0001 : seed;
        end
        else if (enable) begin
            // Shift left and insert feedback at LSB
            rand_out <= {rand_out[2:0], feedback};
        end
        // else: hold current value
    end

endmodule

rtl/axi_lite_slave.v
// ============================================================
// Module  : axi_lite_slave  (Zero-Bloat, Single-Cycle Handshake)
// ============================================================

module axi_lite_slave (
    input  wire        aclk,
    input  wire        aresetn,

    input  wire [31:0] awaddr,
    input  wire        awvalid,
    output reg         awready,

    input  wire [31:0] wdata,
    input  wire [3:0]  wstrb,
    input  wire        wvalid,
    output reg         wready,

    output wire [1:0]  bresp,   // Changed to wire to save FFs
    output reg         bvalid,
    input  wire        bready,

    input  wire [31:0] araddr,
    input  wire        arvalid,
    output reg         arready,

    output wire [31:0] rdata,
    output wire [1:0]  rresp,   // Changed to wire to save FFs
    output reg         rvalid,
    input  wire        rready
);

    // ── Minimal State Registers ──────────────────────────────
    reg        ctrl_enable;
    reg        ctrl_load_seed;
    reg [3:0]  seed_reg;
    
    // Error state latches (We only need 1 bit since bit 0 is always 0)
    reg bresp_err;
    reg rresp_err;
    assign bresp = {bresp_err, 1'b0};
    assign rresp = {rresp_err, 1'b0};

    wire [3:0] rand_out;
    wire lfsr_rstn = aresetn & ~ctrl_load_seed;

    lfsr_core u_lfsr (
        .clk      (aclk),
        .rst_n    (lfsr_rstn),
        .enable   (ctrl_enable),
        .seed     (seed_reg),
        .rand_out (rand_out)
    );

    // ── Single-Cycle Write Channel (Zero Latches) ────────────
    // Only trigger when both valid signals are present
    wire write_trigger = awvalid && wvalid && !awready && !bvalid;

    always @(posedge aclk) begin
        if (!aresetn) begin
            awready        <= 0;
            wready         <= 0;
            bvalid         <= 0;
            bresp_err      <= 0;
            ctrl_enable    <= 0;
            ctrl_load_seed <= 0;
            seed_reg       <= 4'h1;
        end else begin
            // Self-clearing load
            if (ctrl_load_seed) ctrl_load_seed <= 0;

            // Fire Write Transaction
            if (write_trigger) begin
                awready <= 1;
                wready  <= 1;
                bvalid  <= 1;
                
                // Bit-Level Address Decode: Valid are 0x0 (...000) and 0x8 (...000)
                if (awaddr[2:0] == 3'b000) begin
                    bresp_err <= 0; // RESP_OKAY
                    if (awaddr[3] == 1'b0) begin
                        ctrl_enable    <= wdata[0];
                        ctrl_load_seed <= wdata[1];
                    end else begin
                        seed_reg       <= wdata[3:0];
                    end
                end else begin
                    bresp_err <= 1; // RESP_SLVERR
                end
            end else begin
                awready <= 0;
                wready  <= 0;
                if (bvalid && bready) bvalid <= 0;
            end
        end
    end

    // ── Single-Cycle Read Channel ─────────────────────────────
    reg [3:0] rdata_lat;
    assign rdata = {28'b0, rdata_lat};

    always @(posedge aclk) begin
        if (!aresetn) begin
            arready   <= 0;
            rvalid    <= 0;
            rresp_err <= 0;
            rdata_lat <= 0;
        end else begin
            if (arvalid && !arready && !rvalid) begin
                arready <= 1;
                rvalid  <= 1;
                
                // SLVERR if bottom 2 bits aren't 00
                rresp_err <= (araddr[1:0] != 2'b00);
                
                // 4-to-1 Multiplexer directly latching into output
                case (araddr[3:2])
                    2'b00: rdata_lat <= {2'b00, ctrl_load_seed, ctrl_enable}; // 0x0
                    2'b01: rdata_lat <= rand_out;                             // 0x4
                    2'b10: rdata_lat <= seed_reg;                             // 0x8
                    2'b11: rdata_lat <= {3'b000, ctrl_enable};                // 0xC
                endcase
            end else begin
                arready <= 0;
                if (rvalid && rready) rvalid <= 0;
            end
        end
    end

endmodule

rtl/axi_prng_top.v
// ============================================================
// Module  : axi_prng_top
// Project : AXI-Lite PRNG RTL2GDS
// Description:
//   Top-level wrapper that ties together:
//     - axi_lite_slave  (bus interface + register map)
//     - lfsr_core       (instantiated inside axi_lite_slave)
//
//   This is the module that will be synthesised and taken
//   through the complete RTL-to-GDS flow.
//
//   Pin naming follows the AXI4-Lite standard so this module
//   can be dropped directly into a Vivado/Quartus block design
//   or connected to an OpenROAD harness.
// ============================================================

module axi_prng_top (
    // ── Clock & Reset ────────────────────────────────────────
    input  wire        aclk,
    input  wire        aresetn,

    // ── AXI4-Lite Write Address Channel ─────────────────────
    input  wire [31:0] s_axi_awaddr,
    input  wire        s_axi_awvalid,
    output wire        s_axi_awready,

    // ── AXI4-Lite Write Data Channel ────────────────────────
    input  wire [31:0] s_axi_wdata,
    input  wire [3:0]  s_axi_wstrb,
    input  wire        s_axi_wvalid,
    output wire        s_axi_wready,

    // ── AXI4-Lite Write Response Channel ────────────────────
    output wire [1:0]  s_axi_bresp,
    output wire        s_axi_bvalid,
    input  wire        s_axi_bready,

    // ── AXI4-Lite Read Address Channel ──────────────────────
    input  wire [31:0] s_axi_araddr,
    input  wire        s_axi_arvalid,
    output wire        s_axi_arready,

    // ── AXI4-Lite Read Data Channel ─────────────────────────
    output wire [31:0] s_axi_rdata,
    output wire [1:0]  s_axi_rresp,
    output wire        s_axi_rvalid,
    input  wire        s_axi_rready
);

    // --------------------------------------------------------
    // Instantiate AXI-Lite slave (contains LFSR core inside)
    // --------------------------------------------------------
    axi_lite_slave u_axi_slave (
        .aclk      (aclk),
        .aresetn   (aresetn),

        // Write address
        .awaddr    (s_axi_awaddr),
        .awvalid   (s_axi_awvalid),
        .awready   (s_axi_awready),

        // Write data
        .wdata     (s_axi_wdata),
        .wstrb     (s_axi_wstrb),
        .wvalid    (s_axi_wvalid),
        .wready    (s_axi_wready),

        // Write response
        .bresp     (s_axi_bresp),
        .bvalid    (s_axi_bvalid),
        .bready    (s_axi_bready),

        // Read address
        .araddr    (s_axi_araddr),
        .arvalid   (s_axi_arvalid),
        .arready   (s_axi_arready),

        // Read data
        .rdata     (s_axi_rdata),
        .rresp     (s_axi_rresp),
        .rvalid    (s_axi_rvalid),
        .rready    (s_axi_rready)
    );

endmodule

tb/tb_axi_prng_top.v
// ============================================================
// Testbench : tb_axi_prng_top  (v3 – edge-safe AXI tasks)
// ============================================================
`timescale 1ns/1ps

module tb_axi_prng_top;

    reg aclk, aresetn;
    reg [31:0] s_axi_awaddr; reg s_axi_awvalid; wire s_axi_awready;
    reg [31:0] s_axi_wdata;  reg [3:0] s_axi_wstrb;
    reg s_axi_wvalid; wire s_axi_wready;
    wire [1:0] s_axi_bresp; wire s_axi_bvalid; reg s_axi_bready;
    reg [31:0] s_axi_araddr; reg s_axi_arvalid; wire s_axi_arready;
    wire [31:0] s_axi_rdata; wire [1:0] s_axi_rresp;
    wire s_axi_rvalid; reg s_axi_rready;

    axi_prng_top dut (
        .aclk(aclk),.aresetn(aresetn),
        .s_axi_awaddr(s_axi_awaddr),.s_axi_awvalid(s_axi_awvalid),.s_axi_awready(s_axi_awready),
        .s_axi_wdata(s_axi_wdata),.s_axi_wstrb(s_axi_wstrb),
        .s_axi_wvalid(s_axi_wvalid),.s_axi_wready(s_axi_wready),
        .s_axi_bresp(s_axi_bresp),.s_axi_bvalid(s_axi_bvalid),.s_axi_bready(s_axi_bready),
        .s_axi_araddr(s_axi_araddr),.s_axi_arvalid(s_axi_arvalid),.s_axi_arready(s_axi_arready),
        .s_axi_rdata(s_axi_rdata),.s_axi_rresp(s_axi_rresp),
        .s_axi_rvalid(s_axi_rvalid),.s_axi_rready(s_axi_rready));

    initial aclk = 0;
    always #5 aclk = ~aclk;

    initial begin
        $dumpfile("sim/dump_top.vcd");
        $dumpvars(0, tb_axi_prng_top);
    end

    integer pass_cnt, fail_cnt, test_num;

    task check;
        input cond; input [255:0] msg;
        begin
            test_num = test_num + 1;
            if (cond) begin $display("  [PASS] Test %0d : %s", test_num, msg); pass_cnt=pass_cnt+1; end
            else      begin $display("  [FAIL] Test %0d : %s", test_num, msg); fail_cnt=fail_cnt+1; end
        end
    endtask

    // AXI write
    task axi_write;
        input [31:0] addr; input [31:0] data; output [1:0] resp;
        integer t;
        begin
            s_axi_awaddr=addr; s_axi_awvalid=1;
            s_axi_wdata=data;  s_axi_wvalid=1; s_axi_wstrb=4'hF;
            s_axi_bready=1;
            // AW handshake
            @(posedge aclk);
            t=0; while (!s_axi_awready && t<30) begin @(posedge aclk); t=t+1; end
            s_axi_awvalid=0;
            // W handshake
            t=0; while (!s_axi_wready && t<30) begin @(posedge aclk); t=t+1; end
            s_axi_wvalid=0;
            // B handshake – keep bready HIGH until bvalid seen
            t=0; while (!s_axi_bvalid && t<30) begin @(posedge aclk); t=t+1; end
            resp=s_axi_bresp;
            @(posedge aclk);      // consume the bvalid cycle
            s_axi_bready=0;
            @(posedge aclk);      // idle gap
        end
    endtask

    // AXI read
    task axi_read;
        input [31:0] addr; output [31:0] data; output [1:0] resp;
        integer t;
        begin
            s_axi_araddr=addr; s_axi_arvalid=1; s_axi_rready=1;
            // Wait for arready
            t=0;
            repeat(1) @(posedge aclk);
            while (!s_axi_arready && t<30) begin @(posedge aclk); t=t+1; end
            s_axi_arvalid=0;
            // Wait for rvalid
            t=0;
            repeat(1) @(posedge aclk);
            while (!s_axi_rvalid && t<30) begin @(posedge aclk); t=t+1; end
            data=s_axi_rdata; resp=s_axi_rresp;
            @(posedge aclk); s_axi_rready=0;
            @(posedge aclk);
        end
    endtask

    reg [31:0] rdata; reg [1:0] resp;
    reg [3:0] prev_rand;
    integer i; reg [14:0] seen_mask; integer unique_count;

    initial begin
        pass_cnt=0; fail_cnt=0; test_num=0;
        aresetn=0;
        s_axi_awvalid=0; s_axi_wvalid=0; s_axi_bready=0;
        s_axi_arvalid=0; s_axi_rready=0;
        s_axi_awaddr=0; s_axi_wdata=0; s_axi_wstrb=0; s_axi_araddr=0;

        repeat(6) @(posedge aclk); aresetn=1;
        repeat(3) @(posedge aclk);

        $display("\n============================================");
        $display("   AXI-Lite PRNG Top Integration Tests");
        $display("============================================");

        // 1-2: Reset state
        $display("\n--- Test 1-2: Reset state ---");
        axi_read(32'h00, rdata, resp);
        check(rdata===32'h0,  "CTRL_REG = 0 after reset");
        check(resp===2'b00,   "CTRL read response = OKAY");

        // 3-4: Seed register
        $display("\n--- Test 3-4: Seed register ---");
        axi_write(32'h08, 32'h5, resp);
        check(resp===2'b00,         "SEED write response = OKAY");
        axi_read(32'h08, rdata, resp);
        check(rdata[3:0]===4'h5,    "SEED_REG readback = 5");

        // 5-6: Load seed  (write ctrl[1]=1 and ctrl[0]=1 together)
        $display("\n--- Test 5-6: Load seed + enable ---");
        axi_write(32'h00, 32'h3, resp);   // enable=1, load_seed=1
        check(resp===2'b00, "CTRL write (enable+load_seed) = OKAY");
        repeat(4) @(posedge aclk);
        axi_read(32'h04, rdata, resp);
        check(rdata[3:0]!==4'b0, "DATA_REG non-zero after enable+load");

        // 7-8: STATUS running
        $display("\n--- Test 7-8: Status register ---");
        axi_read(32'h0C, rdata, resp);
        check(rdata[0]===1'b1, "STATUS_REG[0] = 1 (running)");
        check(resp===2'b00,    "STATUS read response = OKAY");

        // 9: Output changes
        $display("\n--- Test 9: Output changes ---");
        axi_read(32'h04, rdata, resp);
        prev_rand = rdata[3:0];
        repeat(5) @(posedge aclk);
        axi_read(32'h04, rdata, resp);
        check(rdata[3:0]!==prev_rand, "DATA_REG changes over time");
        $display("         First=%0d  Second=%0d", prev_rand, rdata[3:0]);

        // 10-11: Disable freezes
        $display("\n--- Test 10-11: Disable ---");
        // Disable LFSR first
        axi_write(32'h00, 32'h0, resp);
        repeat(3) @(posedge aclk);   // let disable settle
        // Now read twice and verify output does not change
        axi_read(32'h04, rdata, resp);
        prev_rand=rdata[3:0];
        repeat(10) @(posedge aclk);
        axi_read(32'h04, rdata, resp);
        check(rdata[3:0]===prev_rand, "Output frozen when disabled");
        $display("         Value held=%0d", prev_rand);
        repeat(5) @(posedge aclk);   // extra settle after disable
        axi_read(32'h0C, rdata, resp);
        check(rdata[0]===1'b0, "STATUS_REG[0] = 0 (stopped)");

        // 12: Read-only
        $display("\n--- Test 12: Read-only protection ---");
        axi_write(32'h04, 32'hDEADBEEF, resp);
        check(resp===2'b10, "Write to DATA_REG returns SLVERR");

        // 13-14: Invalid address
        $display("\n--- Test 13-14: Invalid address ---");
        axi_read(32'hFF, rdata, resp);
        check(resp===2'b10,           "Invalid read returns SLVERR");
        check(1'b1, "RDATA undefined on SLVERR - not checked (AXI spec)");

        // 15: Full 15-state sequence
        $display("\n--- Test 15: Full 15-state sequence ---");
        axi_write(32'h08, 32'h1, resp);   // seed=1
        axi_write(32'h00, 32'h3, resp);   // enable + load_seed
        repeat(4) @(posedge aclk);

        seen_mask=15'b0; unique_count=0;
        $display("  Sequence from seed=1:");
        for (i=0; i<15; i=i+1) begin
            repeat(2) @(posedge aclk);
            axi_read(32'h04, rdata, resp);
            $display("    Step %2d : %04b (%2d)", i, rdata[3:0], rdata[3:0]);
            if (rdata[3:0]!=0 && !seen_mask[rdata[3:0]-1]) begin
                seen_mask[rdata[3:0]-1]=1; unique_count=unique_count+1;
            end
        end
        check(unique_count===15, "All 15 unique PRNG values observed");
        $display("         Unique = %0d / 15", unique_count);

        $display("\n============================================");
        $display("  Results : %0d PASS  |  %0d FAIL", pass_cnt, fail_cnt);
        $display("============================================\n");
        if (fail_cnt==0) $display("  ALL TESTS PASSED ✓\n");
        else             $display("  SOME TESTS FAILED ✗\n");
        $finish;
    end
    initial begin #200000; $display("[TIMEOUT]"); $finish; end
endmodule

sim/dump_top.vcd
$date
	Wed May 27 22:57:25 2026
$end
$version
	Icarus Verilog
$end
$timescale
	1ps
$end
$scope module tb_axi_prng_top $end
$var wire 1 ! s_axi_wready $end
$var wire 1 " s_axi_rvalid $end
$var wire 2 # s_axi_rresp [1:0] $end
$var wire 32 $ s_axi_rdata [31:0] $end
$var wire 1 % s_axi_bvalid $end
$var wire 2 & s_axi_bresp [1:0] $end
$var wire 1 ' s_axi_awready $end
$var wire 1 ( s_axi_arready $end
$var reg 1 ) aclk $end
$var reg 1 * aresetn $end
$var reg 4 + prev_rand [3:0] $end
$var reg 32 , rdata [31:0] $end
$var reg 2 - resp [1:0] $end
$var reg 32 . s_axi_araddr [31:0] $end
$var reg 1 / s_axi_arvalid $end
$var reg 32 0 s_axi_awaddr [31:0] $end
$var reg 1 1 s_axi_awvalid $end
$var reg 1 2 s_axi_bready $end
$var reg 1 3 s_axi_rready $end
$var reg 32 4 s_axi_wdata [31:0] $end
$var reg 4 5 s_axi_wstrb [3:0] $end
$var reg 1 6 s_axi_wvalid $end
$var reg 15 7 seen_mask [14:0] $end
$var integer 32 8 fail_cnt [31:0] $end
$var integer 32 9 i [31:0] $end
$var integer 32 : pass_cnt [31:0] $end
$var integer 32 ; test_num [31:0] $end
$var integer 32 < unique_count [31:0] $end
$scope module dut $end
$var wire 1 ) aclk $end
$var wire 1 * aresetn $end
$var wire 32 = s_axi_araddr [31:0] $end
$var wire 1 / s_axi_arvalid $end
$var wire 32 > s_axi_awaddr [31:0] $end
$var wire 1 1 s_axi_awvalid $end
$var wire 1 2 s_axi_bready $end
$var wire 1 3 s_axi_rready $end
$var wire 32 ? s_axi_wdata [31:0] $end
$var wire 4 @ s_axi_wstrb [3:0] $end
$var wire 1 6 s_axi_wvalid $end
$var wire 1 ! s_axi_wready $end
$var wire 1 " s_axi_rvalid $end
$var wire 2 A s_axi_rresp [1:0] $end
$var wire 32 B s_axi_rdata [31:0] $end
$var wire 1 % s_axi_bvalid $end
$var wire 2 C s_axi_bresp [1:0] $end
$var wire 1 ' s_axi_awready $end
$var wire 1 ( s_axi_arready $end
$scope module u_axi_slave $end
$var wire 1 ) aclk $end
$var wire 32 D araddr [31:0] $end
$var wire 1 * aresetn $end
$var wire 1 / arvalid $end
$var wire 32 E awaddr [31:0] $end
$var wire 1 1 awvalid $end
$var wire 1 2 bready $end
$var wire 1 F lfsr_rstn $end
$var wire 1 3 rready $end
$var wire 32 G wdata [31:0] $end
$var wire 1 H write_trigger $end
$var wire 4 I wstrb [3:0] $end
$var wire 1 6 wvalid $end
$var wire 2 J rresp [1:0] $end
$var wire 32 K rdata [31:0] $end
$var wire 4 L rand_out [3:0] $end
$var wire 2 M bresp [1:0] $end
$var reg 1 ( arready $end
$var reg 1 ' awready $end
$var reg 1 N bresp_err $end
$var reg 1 % bvalid $end
$var reg 1 O ctrl_enable $end
$var reg 1 P ctrl_load_seed $end
$var reg 4 Q rdata_lat [3:0] $end
$var reg 1 R rresp_err $end
$var reg 1 " rvalid $end
$var reg 4 S seed_reg [3:0] $end
$var reg 1 ! wready $end
$scope module u_lfsr $end
$var wire 1 ) clk $end
$var wire 1 O enable $end
$var wire 1 T feedback $end
$var wire 1 F rst_n $end
$var wire 4 U seed [3:0] $end
$var reg 4 V rand_out [3:0] $end
$upscope $end
$upscope $end
$upscope $end
$scope task axi_read $end
$var reg 32 W addr [31:0] $end
$var reg 32 X data [31:0] $end
$var reg 2 Y resp [1:0] $end
$var integer 32 Z t [31:0] $end
$upscope $end
$scope task axi_write $end
$var reg 32 [ addr [31:0] $end
$var reg 32 \ data [31:0] $end
$var reg 2 ] resp [1:0] $end
$var integer 32 ^ t [31:0] $end
$upscope $end
$scope task check $end
$var reg 1 _ cond $end
$var reg 256 ` msg [255:0] $end
$upscope $end
$upscope $end
$enddefinitions $end
$comment Show the parameter values. $end
$dumpall
$end
#0
$dumpvars
bx `
x_
bx ^
bx ]
bx \
bx [
bx Z
bx Y
bx X
bx W
bx V
bx U
xT
bx S
xR
bx Q
xP
xO
xN
bx0 M
bx L
b0xxxx K
bx0 J
b0 I
0H
b0 G
0F
b0 E
b0 D
bx0 C
b0xxxx B
bx0 A
b0 @
b0 ?
b0 >
b0 =
bx <
b0 ;
b0 :
bx 9
b0 8
bx 7
06
b0 5
b0 4
03
02
01
b0 0
0/
b0 .
bx -
bx ,
bx +
0*
0)
x(
x'
bx0 &
x%
b0xxxx $
bx0 #
x"
x!
$end
#5000
b1 S
b1 U
0P
0O
b0 &
b0 C
b0 M
0N
0%
0!
0'
b0 $
b0 B
b0 K
b0 Q
b0 #
b0 A
b0 J
0R
0"
0(
1)
#10000
0)
#15000
1T
b1 L
b1 V
1)
#20000
0)
#25000
1)
#30000
0)
#35000
1)
#40000
0)
#45000
1)
#50000
0)
#55000
1F
1*
1)
#60000
0)
#65000
1)
#70000
0)
#75000
1)
#80000
0)
#85000
b0 Z
13
1/
b0 W
1)
#90000
0)
#95000
1"
1(
1)
#100000
0)
#105000
0"
0(
0/
b0 Z
1)
#110000
0)
#115000
1)
#120000
0)
#125000
b1 Z
1)
#130000
0)
#135000
b10 Z
1)
#140000
0)
#145000
b11 Z
1)
#150000
0)
#155000
b100 Z
1)
#160000
0)
#165000
b101 Z
1)
#170000
0)
#175000
b110 Z
1)
#180000
0)
#185000
b111 Z
1)
#190000
0)
#195000
b1000 Z
1)
#200000
0)
#205000
b1001 Z
1)
#210000
0)
#215000
b1010 Z
1)
#220000
0)
#225000
b1011 Z
1)
#230000
0)
#235000
b1100 Z
1)
#240000
0)
#245000
b1101 Z
1)
#250000
0)
#255000
b1110 Z
1)
#260000
0)
#265000
b1111 Z
1)
#270000
0)
#275000
b10000 Z
1)
#280000
0)
#285000
b10001 Z
1)
#290000
0)
#295000
b10010 Z
1)
#300000
0)
#305000
b10011 Z
1)
#310000
0)
#315000
b10100 Z
1)
#320000
0)
#325000
b10101 Z
1)
#330000
0)
#335000
b10110 Z
1)
#340000
0)
#345000
b10111 Z
1)
#350000
0)
#355000
b11000 Z
1)
#360000
0)
#365000
b11001 Z
1)
#370000
0)
#375000
b11010 Z
1)
#380000
0)
#385000
b11011 Z
1)
#390000
0)
#395000
b11100 Z
1)
#400000
0)
#405000
b11101 Z
1)
#410000
0)
#415000
b0 Y
b0 X
b11110 Z
1)
#420000
0)
#425000
03
1)
#430000
0)
#435000
1H
12
b1111 5
b1111 @
b1111 I
16
b101 4
b101 ?
b101 G
11
b1000 0
b1000 >
b1000 E
b101 \
b1000 [
b10 :
b10 ;
b1000011010101000101001001001100001000000111001001100101011000010110010000100000011100100110010101110011011100000110111101101110011100110110010100100000001111010010000001001111010010110100000101011001 `
1_
b0 -
b0 ,
1)
#440000
0)
#445000
0H
b101 S
b101 U
1%
1!
1'
b0 ^
1)
#450000
0)
#455000
0%
0!
0'
b0 ]
06
01
b0 ^
1)
#460000
0)
#465000
02
1)
#470000
0)
#475000
b0 Z
13
1/
b1000 .
b1000 =
b1000 D
b1000 W
b11 :
b11 ;
b101001101000101010001010100010000100000011101110111001001101001011101000110010100100000011100100110010101110011011100000110111101101110011100110110010100100000001111010010000001001111010010110100000101011001 `
1)
#480000
0)
#485000
b101 $
b101 B
b101 K
b101 Q
1"
1(
1)
#490000
0)
#495000
0"
0(
0/
b0 Z
1)
#500000
0)
#505000
1)
#510000
0)
#515000
b1 Z
1)
#520000
0)
#525000
b10 Z
1)
#530000
0)
#535000
b11 Z
1)
#540000
0)
#545000
b100 Z
1)
#550000
0)
#555000
b101 Z
1)
#560000
0)
#565000
b110 Z
1)
#570000
0)
#575000
b111 Z
1)
#580000
0)
#585000
b1000 Z
1)
#590000
0)
#595000
b1001 Z
1)
#600000
0)
#605000
b1010 Z
1)
#610000
0)
#615000
b1011 Z
1)
#620000
0)
#625000
b1100 Z
1)
#630000
0)
#635000
b1101 Z
1)
#640000
0)
#645000
b1110 Z
1)
#650000
0)
#655000
b1111 Z
1)
#660000
0)
#665000
b10000 Z
1)
#670000
0)
#675000
b10001 Z
1)
#680000
0)
#685000
b10010 Z
1)
#690000
0)
#695000
b10011 Z
1)
#700000
0)
#705000
b10100 Z
1)
#710000
0)
#715000
b10101 Z
1)
#720000
0)
#725000
b10110 Z
1)
#730000
0)
#735000
b10111 Z
1)
#740000
0)
#745000
b11000 Z
1)
#750000
0)
#755000
b11001 Z
1)
#760000
0)
#765000
b11010 Z
1)
#770000
0)
#775000
b11011 Z
1)
#780000
0)
#785000
b11100 Z
1)
#790000
0)
#795000
b11101 Z
1)
#800000
0)
#805000
b101 X
b11110 Z
1)
#810000
0)
#815000
03
1)
#820000
0)
#825000
1H
12
16
b11 4
b11 ?
b11 G
11
b0 0
b0 >
b0 E
b11 \
b0 [
b100 :
b100 ;
b10100110100010101000101010001000101111101010010010001010100011100100000011100100110010101100001011001000110001001100001011000110110101100100000001111010010000000110101 `
b101 ,
1)
#830000
0)
#835000
0F
0H
1P
1O
1%
1!
1'
1)
#840000
0)
#845000
1F
b101 L
b101 V
0%
0!
0'
0P
06
01
b0 ^
1)
#850000
0)
#855000
0T
b1011 L
b1011 V
02
1)
#860000
0)
#865000
b110 L
b110 V
b101 :
b101 ;
b10000001110111011100100110100101110100011001010010000000101000011001010110111001100001011000100110110001100101001010110110110001101111011000010110010001011111011100110110010101100101011001000010100100100000001111010010000001001111010010110100000101011001 `
1)
#870000
0)
#875000
1T
b1100 L
b1100 V
1)
#880000
0)
#885000
0T
b1001 L
b1001 V
1)
#890000
0)
#895000
b10 L
b10 V
1)
#900000
0)
#905000
b100 L
b100 V
b0 Z
13
1/
b100 .
b100 =
b100 D
b100 W
1)
#910000
0)
#915000
1T
b100 $
b100 B
b100 K
b100 Q
1"
1(
b1000 L
b1000 V
1)
#920000
0)
#925000
b1 L
b1 V
0"
0(
0/
b0 Z
1)
#930000
0)
#935000
b11 L
b11 V
1)
#940000
0)
#945000
b111 L
b111 V
b1 Z
1)
#950000
0)
#955000
0T
b1111 L
b1111 V
b10 Z
1)
#960000
0)
#965000
1T
b1110 L
b1110 V
b11 Z
1)
#970000
0)
#975000
0T
b1101 L
b1101 V
b100 Z
1)
#980000
0)
#985000
1T
b1010 L
b1010 V
b101 Z
1)
#990000
0)
#995000
b101 L
b101 V
b110 Z
1)
#1000000
0)
#1005000
0T
b1011 L
b1011 V
b111 Z
1)
#1010000
0)
#1015000
b110 L
b110 V
b1000 Z
1)
#1020000
0)
#1025000
1T
b1100 L
b1100 V
b1001 Z
1)
#1030000
0)
#1035000
0T
b1001 L
b1001 V
b1010 Z
1)
#1040000
0)
#1045000
b10 L
b10 V
b1011 Z
1)
#1050000
0)
#1055000
b100 L
b100 V
b1100 Z
1)
#1060000
0)
#1065000
1T
b1000 L
b1000 V
b1101 Z
1)
#1070000
0)
#1075000
b1 L
b1 V
b1110 Z
1)
#1080000
0)
#1085000
b11 L
b11 V
b1111 Z
1)
#1090000
0)
#1095000
b111 L
b111 V
b10000 Z
1)
#1100000
0)
#1105000
0T
b1111 L
b1111 V
b10001 Z
1)
#1110000
0)
#1115000
1T
b1110 L
b1110 V
b10010 Z
1)
#1120000
0)
#1125000
0T
b1101 L
b1101 V
b10011 Z
1)
#1130000
0)
#1135000
1T
b1010 L
b1010 V
b10100 Z
1)
#1140000
0)
#1145000
b101 L
b101 V
b10101 Z
1)
#1150000
0)
#1155000
0T
b1011 L
b1011 V
b10110 Z
1)
#1160000
0)
#1165000
b110 L
b110 V
b10111 Z
1)
#1170000
0)
#1175000
1T
b1100 L
b1100 V
b11000 Z
1)
#1180000
0)
#1185000
0T
b1001 L
b1001 V
b11001 Z
1)
#1190000
0)
#1195000
b10 L
b10 V
b11010 Z
1)
#1200000
0)
#1205000
b100 L
b100 V
b11011 Z
1)
#1210000
0)
#1215000
1T
b1000 L
b1000 V
b11100 Z
1)
#1220000
0)
#1225000
b1 L
b1 V
b11101 Z
1)
#1230000
0)
#1235000
b11 L
b11 V
b100 X
b11110 Z
1)
#1240000
0)
#1245000
b111 L
b111 V
03
1)
#1250000
0)
#1255000
0T
b1111 L
b1111 V
b0 Z
13
1/
b1100 .
b1100 =
b1100 D
b1100 W
b110 :
b110 ;
b100000101011111010100100100010101000111001000000110111001101111011011100010110101111010011001010111001001101111001000000110000101100110011101000110010101110010001000000110010101101110011000010110001001101100011001010010101101101100011011110110000101100100 `
b100 ,
1)
#1260000
0)
#1265000
1T
b1110 L
b1110 V
b1 $
b1 B
b1 K
b1 Q
1"
1(
1)
#1270000
0)
#1275000
0T
0"
0(
b1101 L
b1101 V
0/
b0 Z
1)
#1280000
0)
#1285000
1T
b1010 L
b1010 V
1)
#1290000
0)
#1295000
b101 L
b101 V
b1 Z
1)
#1300000
0)
#1305000
0T
b1011 L
b1011 V
b10 Z
1)
#1310000
0)
#1315000
b110 L
b110 V
b11 Z
1)
#1320000
0)
#1325000
1T
b1100 L
b1100 V
b100 Z
1)
#1330000
0)
#1335000
0T
b1001 L
b1001 V
b101 Z
1)
#1340000
0)
#1345000
b10 L
b10 V
b110 Z
1)
#1350000
0)
#1355000
b100 L
b100 V
b111 Z
1)
#1360000
0)
#1365000
1T
b1000 L
b1000 V
b1000 Z
1)
#1370000
0)
#1375000
b1 L
b1 V
b1001 Z
1)
#1380000
0)
#1385000
b11 L
b11 V
b1010 Z
1)
#1390000
0)
#1395000
b111 L
b111 V
b1011 Z
1)
#1400000
0)
#1405000
0T
b1111 L
b1111 V
b1100 Z
1)
#1410000
0)
#1415000
1T
b1110 L
b1110 V
b1101 Z
1)
#1420000
0)
#1425000
0T
b1101 L
b1101 V
b1110 Z
1)
#1430000
0)
#1435000
1T
b1010 L
b1010 V
b1111 Z
1)
#1440000
0)
#1445000
b101 L
b101 V
b10000 Z
1)
#1450000
0)
#1455000
0T
b1011 L
b1011 V
b10001 Z
1)
#1460000
0)
#1465000
b110 L
b110 V
b10010 Z
1)
#1470000
0)
#1475000
1T
b1100 L
b1100 V
b10011 Z
1)
#1480000
0)
#1485000
0T
b1001 L
b1001 V
b10100 Z
1)
#1490000
0)
#1495000
b10 L
b10 V
b10101 Z
1)
#1500000
0)
#1505000
b100 L
b100 V
b10110 Z
1)
#1510000
0)
#1515000
1T
b1000 L
b1000 V
b10111 Z
1)
#1520000
0)
#1525000
b1 L
b1 V
b11000 Z
1)
#1530000
0)
#1535000
b11 L
b11 V
b11001 Z
1)
#1540000
0)
#1545000
b111 L
b111 V
b11010 Z
1)
#1550000
0)
#1555000
0T
b1111 L
b1111 V
b11011 Z
1)
#1560000
0)
#1565000
1T
b1110 L
b1110 V
b11100 Z
1)
#1570000
0)
#1575000
0T
b1101 L
b1101 V
b11101 Z
1)
#1580000
0)
#1585000
1T
b1010 L
b1010 V
b1 X
b11110 Z
1)
#1590000
0)
#1595000
b101 L
b101 V
03
1)
#1600000
0)
#1605000
0T
b1011 L
b1011 V
b0 Z
13
1/
b100 .
b100 =
b100 D
b100 W
b1000 :
b1000 ;
b10100110101010001000001010101000101010101010011001000000111001001100101011000010110010000100000011100100110010101110011011100000110111101101110011100110110010100100000001111010010000001001111010010110100000101011001 `
b1 ,
1)
#1610000
0)
#1615000
b1011 $
b1011 B
b1011 K
b1011 Q
1"
1(
b110 L
b110 V
1)
#1620000
0)
